vostok/__init__.py
vostok-0.1.0.dist-info/LICENSE
vostok-0.1.0.dist-info/METADATA
vostok-0.1.0.dist-info/WHEEL
vostok-0.1.0.dist-info/top_level.txt
vostok-0.1.0.dist-info/RECORD
