Metadata-Version: 2.1
Name: vostok
Version: 0.1.0
Summary: A chagelog parser for Keep a Changelog format
Home-page: https://github.com/vitorbaraujo/vostok
Author: vitorbaraujo
Author-email: vitornga15@gmail.com
License: UNKNOWN
Platform: UNKNOWN
Classifier: Programming Language :: Python :: 3
Classifier: License :: OSI Approved :: MIT License
Classifier: Operating System :: OS Independent
Requires-Python: >=3.6
